.gitignore
.pre-commit-config.yaml
.pylintrc
CHANGELOG.md
LICENSE
NOTICE
README.md
pyproject.toml
setup.cfg
setup.py
sonar-project.properties
.github/workflows/mccnn_ci.yml
MCCNN.egg-info/PKG-INFO
MCCNN.egg-info/SOURCES.txt
MCCNN.egg-info/dependency_links.txt
MCCNN.egg-info/requires.txt
MCCNN.egg-info/top_level.txt
doc/Makefile
doc/make.bat
doc/sources/conf.py
doc/sources/getting_started.rst
doc/sources/index.rst
doc/sources/Images/mc_cnn_architectures.svg
doc/sources/Images/logo/logo_typo_large.png
doc/sources/_static/css/my_custom.css
doc/sources/getting_started/quick_overview.rst
doc/sources/getting_started/run_mc_cnn.rst
doc/sources/getting_started/train_mc_cnn.rst
mc_cnn/__init__.py
mc_cnn/run.py
mc_cnn/train.py
mc_cnn/dataset_generator/__init__.py
mc_cnn/dataset_generator/datas_fusion_contest_generator.py
mc_cnn/dataset_generator/middlebury_generator.py
mc_cnn/model/__init__.py
mc_cnn/model/mc_cnn_accurate.py
mc_cnn/model/mc_cnn_fast.py
mc_cnn/preprocessing/__init__.py
mc_cnn/preprocessing/preprocess_middlebury.py
mc_cnn/preprocessing/preprocessing_beefrost_data_fusion_contest.py
mc_cnn/training_config/train_data_fusion_contest.json
mc_cnn/training_config/train_mb_accurate.json
mc_cnn/training_config/train_mb_fast.json
mc_cnn/weights/__init__.py
mc_cnn/weights/mc_cnn_accurate_data_fusion_contest.pt
mc_cnn/weights/mc_cnn_accurate_mb_weights.pt
mc_cnn/weights/mc_cnn_fast_data_fusion_contest.pt
mc_cnn/weights/mc_cnn_fast_mb_weights.pt
mc_cnn/weights/weights.py
tests/images_dfc.hdf5
tests/images_middlebury.hdf5
tests/sample_dfc.hdf5
tests/sample_middlebury.hdf5
tests/test_mc_cnn.py