Metadata-Version: 2.1
Name: MCCNN
Version: 1.1.0
Summary: MCCNN is a neural network for learning a similarity measure on image patches
Home-page: https://github.com/CNES/Pandora_MCCNN
Author: CNES
Author-email: myriam.cournet@cnes.fr
License: Apache License 2.0
Requires-Python: >=3.7
Provides-Extra: dev
Provides-Extra: docs
License-File: LICENSE
